seedcase_sprout/__init__.py
seedcase_sprout/as_readme_text.py
seedcase_sprout/check_data.py
seedcase_sprout/check_properties.py
seedcase_sprout/constants.py
seedcase_sprout/create_properties_script.py
seedcase_sprout/create_resource_properties_script.py
seedcase_sprout/examples.py
seedcase_sprout/extract_field_properties.py
seedcase_sprout/join_resource_batches.py
seedcase_sprout/map_data_types.py
seedcase_sprout/paths.py
seedcase_sprout/properties.py
seedcase_sprout/py.typed
seedcase_sprout/read_properties.py
seedcase_sprout/read_resource_batches.py
seedcase_sprout/read_resource_data.py
seedcase_sprout/write_file.py
seedcase_sprout/write_properties.py
seedcase_sprout/write_resource_batch.py
seedcase_sprout/write_resource_data.py
seedcase_sprout/internals/__init__.py
seedcase_sprout/internals/check.py
seedcase_sprout/internals/create.py
seedcase_sprout/internals/functionals.py
seedcase_sprout/internals/get.py
seedcase_sprout/internals/read.py
seedcase_sprout/internals/to.py
seedcase_sprout/internals/write.py
seedcase_sprout/sprout_checks/__init__.py
seedcase_sprout/sprout_checks/is_resource_name_correct.py
seedcase_sprout/sprout_checks/required_fields.py
seedcase_sprout/templates/README.jinja2
seedcase_sprout/templates/field_properties.jinja2
seedcase_sprout/templates/package_properties.py.jinja2
seedcase_sprout/templates/resource_properties.py.jinja2
seedcase_sprout-0.49.1.dist-info/METADATA
seedcase_sprout-0.49.1.dist-info/WHEEL
seedcase_sprout-0.49.1.dist-info/licenses/LICENSE.md
seedcase_sprout-0.49.1.dist-info/RECORD
