Metadata-Version: 2.4
Name: seedcase-sprout
Version: 0.49.1
Summary: Grow your research data in a structured, modern way that follows best practices.
Project-URL: homepage, https://sprout.seedcase-project.org
Project-URL: repository, https://github.com/seedcase-project/seedcase-sprout
Project-URL: changelog, https://github.com/seedcase-project/seedcase-sprout/blob/main/CHANGELOG.md
Project-URL: issues, https://github.com/seedcase-project/seedcase-sprout/issues
Author-email: "Luke W. Johnston" <lwjohnst@gmail.com>, Kristiane Beicher <kris.beicher@clin.au.dk>, Signe Kirk Brødbæk <signekb@clin.au.dk>, Marton Vago <marton.vago95@gmail.com>
Maintainer-email: "Luke W. Johnston" <lwjohnst@gmail.com>, Kristiane Beicher <kris.beicher@clin.au.dk>, Signe Kirk Brødbæk <signekb@clin.au.dk>, Marton Vago <marton.vago95@gmail.com>
License-Expression: MIT
License-File: LICENSE.md
Keywords: data,data checks,data engineering,data infrastructure,data management,data organization,data package,data package checks,data structure,data verification,framework,frictionless
Requires-Python: >=3.12
Requires-Dist: check-datapackage>=0.23.1
Requires-Dist: dacite>=1.9.2
Requires-Dist: deepmerge>=2.0
Requires-Dist: jinja2>=3.1.6
Requires-Dist: jsonschema>=4.23.0
Requires-Dist: polars>=1.26.0
